athena_starship/__init__.py
athena_starship/data_connectors.py
athena_starship/ghost_datasource_urls.py
athena_starship/llama.py
athena_starship/memory.py
athena_starship/tool_schemas.py
athena_starship/tools/__init__.py
athena_starship/tools/google_calendar.py
athena_starship/youtube_utils.py
athena_starship-0.0.6.dist-info/LICENSE
athena_starship-0.0.6.dist-info/WHEEL
athena_starship-0.0.6.dist-info/METADATA
athena_starship-0.0.6.dist-info/RECORD
